clevr_parser/__init__.py
clevr_parser/_version.py
clevr_parser/database.py
clevr_parser/explacy.py
clevr_parser/parser.py
clevr_parser/utils.py
clevr_parser/backends/__init__.py
clevr_parser/backends/backend.py
clevr_parser/backends/custom_components_clevr.py
clevr_parser/backends/spacy_parser.py
clevr_parser/backends/stanfordnlp_parser.py
clevr_parser-0.0.6.dist-info/LICENSE
clevr_parser-0.0.6.dist-info/METADATA
clevr_parser-0.0.6.dist-info/WHEEL
clevr_parser-0.0.6.dist-info/top_level.txt
clevr_parser-0.0.6.dist-info/RECORD
