Metadata-Version: 2.1
Name: clevr-parser
Version: 0.0.6
Summary: PGM factoring, object candidate proposal generator for CLEVR dataset
Home-page: https://github.com/raeidsaqur/clevr-parser
Author: Raeid Saqur
Author-email: raeidsaqur@cs.toronto.edu
License: UNKNOWN
Keywords: pytorch,CLEVR,language compositionality,geometric learning,graph neural networks
Platform: UNKNOWN
Classifier: Programming Language :: Python :: 3
Classifier: License :: OSI Approved :: MIT License
Classifier: Operating System :: OS Independent
Requires-Python: >=3.6
Requires-Dist: numpy
Requires-Dist: scipy
Requires-Dist: networkx
Requires-Dist: scikit-learn
Requires-Dist: scikit-image
Requires-Dist: requests
Requires-Dist: tabulate
Requires-Dist: stanfordnlp
Requires-Dist: spacy-transformers
